astro_meshless_surfaces/__init__.py
astro_meshless_surfaces/deprecated.py
astro_meshless_surfaces/kernels.py
astro_meshless_surfaces/meshless.py
astro_meshless_surfaces/meshlessio.py
astro_meshless_surfaces/optional_packages.py
astro_meshless_surfaces/particles.py
astro_meshless_surfaces-0.1.16.dist-info/LICENSE.txt
astro_meshless_surfaces-0.1.16.dist-info/METADATA
astro_meshless_surfaces-0.1.16.dist-info/WHEEL
astro_meshless_surfaces-0.1.16.dist-info/top_level.txt
astro_meshless_surfaces-0.1.16.dist-info/RECORD
