Metadata-Version: 2.1
Name: astro-meshless-surfaces
Version: 0.1.16
Summary: UNKNOWN
Home-page: UNKNOWN
Author: Mladen Ivkovic
Author-email: mladen.ivkovic@hotmail.com
License: GLPv3
Platform: UNKNOWN
Requires-Dist: numpy
Requires-Dist: matplotlib
Requires-Dist: h5py
Requires-Dist: scipy
